pyeilcd/__init__.py
pyeilcd/config.py
pyeilcd/core.py
pyeilcd/schemas/ILCD_Categories.xsd
pyeilcd/schemas/ILCD_Common_DataTypes.xsd
pyeilcd/schemas/ILCD_Common_EnumerationValues.xsd
pyeilcd/schemas/ILCD_Common_Groups.xsd
pyeilcd/schemas/ILCD_Common_Validation.xsd
pyeilcd/schemas/ILCD_ContactDataSet.xsd
pyeilcd/schemas/ILCD_Documentation.xsd
pyeilcd/schemas/ILCD_FlowDataSet.xsd
pyeilcd/schemas/ILCD_FlowPropertyDataSet.xsd
pyeilcd/schemas/ILCD_ILCD.xsd
pyeilcd/schemas/ILCD_LCIAMethodDataSet.xsd
pyeilcd/schemas/ILCD_LCIAMethodologies.xsd
pyeilcd/schemas/ILCD_LifeCycleModelDataSet.xsd
pyeilcd/schemas/ILCD_Locations.xsd
pyeilcd/schemas/ILCD_ProcessDataSet.xsd
pyeilcd/schemas/ILCD_SourceDataSet.xsd
pyeilcd/schemas/ILCD_UnitGroupDataSet.xsd
pyeilcd/schemas/xml.xsd
pyeilcd-7.0.14.dist-info/LICENSE
pyeilcd-7.0.14.dist-info/METADATA
pyeilcd-7.0.14.dist-info/WHEEL
pyeilcd-7.0.14.dist-info/top_level.txt
pyeilcd-7.0.14.dist-info/RECORD
